scriptic/__init__.py
scriptic/scriptic.py
scriptic/version.py
scriptic-0.1.0.dist-info/METADATA
scriptic-0.1.0.dist-info/WHEEL
scriptic-0.1.0.dist-info/entry_points.txt
scriptic-0.1.0.dist-info/top_level.txt
scriptic-0.1.0.dist-info/RECORD
