Metadata-Version: 2.4
Name: scriptic
Version: 0.1.0
Summary: A minimalist embeddable Python REPL / Script Runner.
Author-email: Ryan O'Boyle <layerdynamics@proton.me>
License-Expression: MIT
Project-URL: Homepage, https://github.com/layerdynamics/scriptic
Project-URL: Bug Tracker, https://github.com/layerdynamics/scriptic/issues
Keywords: repl,terminal,interactive,embed,console,script,runner,python,cli,shell,script runner,interactive shell
Classifier: Development Status :: 4 - Beta
Classifier: Intended Audience :: Developers
Classifier: Programming Language :: Python :: 3
Classifier: Programming Language :: Python :: 3.6
Classifier: Programming Language :: Python :: 3.7
Classifier: Programming Language :: Python :: 3.8
Classifier: Programming Language :: Python :: 3.9
Classifier: Programming Language :: Python :: 3.10
Classifier: Programming Language :: Python :: 3.11
Classifier: Topic :: Software Development :: Libraries :: Python Modules
Classifier: Topic :: Software Development :: User Interfaces
Requires-Python: >=3.6
